{
  "project_info": {
    "project_number": "629228057164",
    "project_id": "fit-tracker-59cb4",
    "storage_bucket": "fit-tracker-59cb4.firebasestorage.app"
  },
  "client": [
    {
      "client_info": {
        "mobilesdk_app_id": "1:629228057164:android:86bc4a4c16f8d886f63ae9",
        "android_client_info": {
          "package_name": "com.example.fit_tracker"
        }
      },
      "oauth_client": [],
      "api_key": [
        {
          "current_key": "AIzaSyBMBftZhnTq_Yn7Tnai3kpLats-xW3t5fU"
        }
      ],
      "services": {
        "appinvite_service": {
          "other_platform_oauth_client": []
        }
      }
    }
  ],
  "configuration_version": "1"
}